odoo/addons/l10n_de_tax_statement/README.rst
odoo/addons/l10n_de_tax_statement/__init__.py
odoo/addons/l10n_de_tax_statement/__manifest__.py
odoo/addons/l10n_de_tax_statement/data/paperformat.xml
odoo/addons/l10n_de_tax_statement/i18n/de.po
odoo/addons/l10n_de_tax_statement/i18n/l10n_de_tax_statement.pot
odoo/addons/l10n_de_tax_statement/models/__init__.py
odoo/addons/l10n_de_tax_statement/models/account_move.py
odoo/addons/l10n_de_tax_statement/models/account_move_line.py
odoo/addons/l10n_de_tax_statement/models/account_tax.py
odoo/addons/l10n_de_tax_statement/models/l10n_de_tax_statement.py
odoo/addons/l10n_de_tax_statement/models/l10n_de_tax_statement_2018.py
odoo/addons/l10n_de_tax_statement/models/l10n_de_tax_statement_2019.py
odoo/addons/l10n_de_tax_statement/models/l10n_de_tax_statement_config.py
odoo/addons/l10n_de_tax_statement/models/l10n_de_tax_statement_line.py
odoo/addons/l10n_de_tax_statement/readme/CONFIGURE.rst
odoo/addons/l10n_de_tax_statement/readme/CONTRIBUTORS.rst
odoo/addons/l10n_de_tax_statement/readme/DESCRIPTION.rst
odoo/addons/l10n_de_tax_statement/readme/INSTALL.rst
odoo/addons/l10n_de_tax_statement/readme/ROADMAP.rst
odoo/addons/l10n_de_tax_statement/readme/USAGE.rst
odoo/addons/l10n_de_tax_statement/report/report_tax_statement.xml
odoo/addons/l10n_de_tax_statement/security/ir.model.access.csv
odoo/addons/l10n_de_tax_statement/security/tax_statement_security_rule.xml
odoo/addons/l10n_de_tax_statement/static/description/icon.png
odoo/addons/l10n_de_tax_statement/static/description/index.html
odoo/addons/l10n_de_tax_statement/static/src/css/report.css
odoo/addons/l10n_de_tax_statement/templates/assets.xml
odoo/addons/l10n_de_tax_statement/tests/__init__.py
odoo/addons/l10n_de_tax_statement/tests/test_l10n_de_tax_statement.py
odoo/addons/l10n_de_tax_statement/views/l10n_de_tax_statement_view.xml
odoo/addons/l10n_de_tax_statement/views/report_tax_statement.xml
odoo/addons/l10n_de_tax_statement/wizard/__init__.py
odoo11_addon_l10n_de_tax_statement-11.0.1.1.1.dist-info/METADATA
odoo11_addon_l10n_de_tax_statement-11.0.1.1.1.dist-info/WHEEL
odoo11_addon_l10n_de_tax_statement-11.0.1.1.1.dist-info/top_level.txt
odoo11_addon_l10n_de_tax_statement-11.0.1.1.1.dist-info/RECORD
